<list>
  <Circle>
    <color>
      <red>0</red>
      <green>0</green>
      <blue>0</blue>
      <alpha>255</alpha>
    </color>
    <fill>
      <red>255</red>
      <green>0</green>
      <blue>0</blue>
      <alpha>255</alpha>
    </fill>
    <thickness>3</thickness>
    <isDashed>false</isDashed>
    <isFilled>true</isFilled>
    <boundries>
      <java.awt.geom.Rectangle2D_-Double>
        <x>267.0</x>
        <y>89.0</y>
        <width>8.0</width>
        <height>8.0</height>
      </java.awt.geom.Rectangle2D_-Double>
      <java.awt.geom.Rectangle2D_-Double>
        <x>232.0</x>
        <y>124.0</y>
        <width>8.0</width>
        <height>8.0</height>
      </java.awt.geom.Rectangle2D_-Double>
      <java.awt.geom.Rectangle2D_-Double>
        <x>302.0</x>
        <y>124.0</y>
        <width>8.0</width>
        <height>8.0</height>
      </java.awt.geom.Rectangle2D_-Double>
      <java.awt.geom.Rectangle2D_-Double>
        <x>267.0</x>
        <y>159.0</y>
        <width>8.0</width>
        <height>8.0</height>
      </java.awt.geom.Rectangle2D_-Double>
    </boundries>
    <a>70</a>
    <b>70</b>
    <x>236</x>
    <y>93</y>
    <xBounds>
      <int>271</int>
      <int>236</int>
      <int>306</int>
      <int>271</int>
    </xBounds>
    <yBounds>
      <int>93</int>
      <int>128</int>
      <int>128</int>
      <int>163</int>
    </yBounds>
    <E class="java.awt.geom.Ellipse2D$Double">
      <x>236.0</x>
      <y>93.0</y>
      <width>70.0</width>
      <height>70.0</height>
    </E>
    <isCircle>true</isCircle>
  </Circle>
  <Circle>
    <color reference="../../Circle/color"/>
    <fill reference="../../Circle/fill"/>
    <thickness>3</thickness>
    <isDashed>false</isDashed>
    <isFilled>true</isFilled>
    <boundries>
      <java.awt.geom.Rectangle2D_-Double>
        <x>213.0</x>
        <y>136.0</y>
        <width>8.0</width>
        <height>8.0</height>
      </java.awt.geom.Rectangle2D_-Double>
      <java.awt.geom.Rectangle2D_-Double>
        <x>179.0</x>
        <y>170.0</y>
        <width>8.0</width>
        <height>8.0</height>
      </java.awt.geom.Rectangle2D_-Double>
      <java.awt.geom.Rectangle2D_-Double>
        <x>247.0</x>
        <y>170.0</y>
        <width>8.0</width>
        <height>8.0</height>
      </java.awt.geom.Rectangle2D_-Double>
      <java.awt.geom.Rectangle2D_-Double>
        <x>213.0</x>
        <y>204.0</y>
        <width>8.0</width>
        <height>8.0</height>
      </java.awt.geom.Rectangle2D_-Double>
    </boundries>
    <a>68</a>
    <b>68</b>
    <x>183</x>
    <y>140</y>
    <xBounds>
      <int>217</int>
      <int>183</int>
      <int>251</int>
      <int>217</int>
    </xBounds>
    <yBounds>
      <int>140</int>
      <int>174</int>
      <int>174</int>
      <int>208</int>
    </yBounds>
    <E class="java.awt.geom.Ellipse2D$Double">
      <x>183.0</x>
      <y>140.0</y>
      <width>68.0</width>
      <height>68.0</height>
    </E>
    <isCircle>true</isCircle>
  </Circle>
  <Circle>
    <color reference="../../Circle/color"/>
    <fill reference="../../Circle/fill"/>
    <thickness>3</thickness>
    <isDashed>false</isDashed>
    <isFilled>true</isFilled>
    <boundries>
      <java.awt.geom.Rectangle2D_-Double>
        <x>247.0</x>
        <y>194.0</y>
        <width>8.0</width>
        <height>8.0</height>
      </java.awt.geom.Rectangle2D_-Double>
      <java.awt.geom.Rectangle2D_-Double>
        <x>214.0</x>
        <y>227.0</y>
        <width>8.0</width>
        <height>8.0</height>
      </java.awt.geom.Rectangle2D_-Double>
      <java.awt.geom.Rectangle2D_-Double>
        <x>280.0</x>
        <y>227.0</y>
        <width>8.0</width>
        <height>8.0</height>
      </java.awt.geom.Rectangle2D_-Double>
      <java.awt.geom.Rectangle2D_-Double>
        <x>247.0</x>
        <y>260.0</y>
        <width>8.0</width>
        <height>8.0</height>
      </java.awt.geom.Rectangle2D_-Double>
    </boundries>
    <a>66</a>
    <b>66</b>
    <x>218</x>
    <y>198</y>
    <xBounds>
      <int>251</int>
      <int>218</int>
      <int>284</int>
      <int>251</int>
    </xBounds>
    <yBounds>
      <int>198</int>
      <int>231</int>
      <int>231</int>
      <int>264</int>
    </yBounds>
    <E class="java.awt.geom.Ellipse2D$Double">
      <x>218.0</x>
      <y>198.0</y>
      <width>66.0</width>
      <height>66.0</height>
    </E>
    <isCircle>true</isCircle>
  </Circle>
  <Circle>
    <color reference="../../Circle/color"/>
    <fill reference="../../Circle/fill"/>
    <thickness>3</thickness>
    <isDashed>false</isDashed>
    <isFilled>true</isFilled>
    <boundries>
      <java.awt.geom.Rectangle2D_-Double>
        <x>321.0</x>
        <y>133.0</y>
        <width>8.0</width>
        <height>8.0</height>
      </java.awt.geom.Rectangle2D_-Double>
      <java.awt.geom.Rectangle2D_-Double>
        <x>287.0</x>
        <y>167.0</y>
        <width>8.0</width>
        <height>8.0</height>
      </java.awt.geom.Rectangle2D_-Double>
      <java.awt.geom.Rectangle2D_-Double>
        <x>355.0</x>
        <y>167.0</y>
        <width>8.0</width>
        <height>8.0</height>
      </java.awt.geom.Rectangle2D_-Double>
      <java.awt.geom.Rectangle2D_-Double>
        <x>321.0</x>
        <y>201.0</y>
        <width>8.0</width>
        <height>8.0</height>
      </java.awt.geom.Rectangle2D_-Double>
    </boundries>
    <a>68</a>
    <b>68</b>
    <x>291</x>
    <y>137</y>
    <xBounds>
      <int>325</int>
      <int>291</int>
      <int>359</int>
      <int>325</int>
    </xBounds>
    <yBounds>
      <int>137</int>
      <int>171</int>
      <int>171</int>
      <int>205</int>
    </yBounds>
    <E class="java.awt.geom.Ellipse2D$Double">
      <x>291.0</x>
      <y>137.0</y>
      <width>68.0</width>
      <height>68.0</height>
    </E>
    <isCircle>true</isCircle>
  </Circle>
  <Line>
    <color reference="../../Circle/color"/>
    <thickness>3</thickness>
    <isDashed>false</isDashed>
    <isFilled>false</isFilled>
    <boundries>
      <java.awt.geom.Rectangle2D_-Double>
        <x>365.0</x>
        <y>263.0</y>
        <width>8.0</width>
        <height>8.0</height>
      </java.awt.geom.Rectangle2D_-Double>
      <java.awt.geom.Rectangle2D_-Double>
        <x>281.0</x>
        <y>193.0</y>
        <width>8.0</width>
        <height>8.0</height>
      </java.awt.geom.Rectangle2D_-Double>
    </boundries>
    <x1>369</x1>
    <y1>267</y1>
    <x2>285</x2>
    <y2>197</y2>
    <xBounds>
      <int>369</int>
      <int>285</int>
    </xBounds>
    <yBounds>
      <int>267</int>
      <int>197</int>
    </yBounds>
  </Line>
  <Line>
    <color reference="../../Circle/color"/>
    <thickness>3</thickness>
    <isDashed>false</isDashed>
    <isFilled>false</isFilled>
    <boundries>
      <java.awt.geom.Rectangle2D_-Double>
        <x>382.0</x>
        <y>232.0</y>
        <width>8.0</width>
        <height>8.0</height>
      </java.awt.geom.Rectangle2D_-Double>
      <java.awt.geom.Rectangle2D_-Double>
        <x>367.0</x>
        <y>266.0</y>
        <width>8.0</width>
        <height>8.0</height>
      </java.awt.geom.Rectangle2D_-Double>
    </boundries>
    <x1>386</x1>
    <y1>236</y1>
    <x2>371</x2>
    <y2>270</y2>
    <xBounds>
      <int>386</int>
      <int>371</int>
    </xBounds>
    <yBounds>
      <int>236</int>
      <int>270</int>
    </yBounds>
  </Line>
  <Triangle>
    <color reference="../../Circle/color"/>
    <fill>
      <red>0</red>
      <green>102</green>
      <blue>51</blue>
      <alpha>255</alpha>
    </fill>
    <thickness>3</thickness>
    <isDashed>false</isDashed>
    <isFilled>true</isFilled>
    <boundries>
      <java.awt.geom.Rectangle2D_-Double>
        <x>386.0</x>
        <y>191.0</y>
        <width>8.0</width>
        <height>8.0</height>
      </java.awt.geom.Rectangle2D_-Double>
      <java.awt.geom.Rectangle2D_-Double>
        <x>386.0</x>
        <y>191.0</y>
        <width>8.0</width>
        <height>8.0</height>
      </java.awt.geom.Rectangle2D_-Double>
      <java.awt.geom.Rectangle2D_-Double>
        <x>369.0</x>
        <y>234.0</y>
        <width>8.0</width>
        <height>8.0</height>
      </java.awt.geom.Rectangle2D_-Double>
      <java.awt.geom.Rectangle2D_-Double>
        <x>403.0</x>
        <y>234.0</y>
        <width>8.0</width>
        <height>8.0</height>
      </java.awt.geom.Rectangle2D_-Double>
    </boundries>
    <xPoly>
      <int>407</int>
      <int>373</int>
      <int>373</int>
      <int>407</int>
    </xPoly>
    <yPoly>
      <int>195</int>
      <int>195</int>
      <int>238</int>
      <int>238</int>
    </yPoly>
    <length>4</length>
    <P>
      <npoints>3</npoints>
      <xpoints>
        <int>390</int>
        <int>373</int>
        <int>407</int>
      </xpoints>
      <ypoints>
        <int>195</int>
        <int>238</int>
        <int>238</int>
      </ypoints>
      <bounds>
        <x>373</x>
        <y>195</y>
        <width>34</width>
        <height>43</height>
      </bounds>
    </P>
    <isRegular>false</isRegular>
    <triX>
      <int>390</int>
      <int>373</int>
      <int>407</int>
    </triX>
    <triY>
      <int>195</int>
      <int>238</int>
      <int>238</int>
    </triY>
  </Triangle>
  <Line>
    <color>
      <red>0</red>
      <green>0</green>
      <blue>0</blue>
      <alpha>255</alpha>
    </color>
    <thickness>3</thickness>
    <isDashed>false</isDashed>
    <isFilled>false</isFilled>
    <boundries>
      <java.awt.geom.Rectangle2D_-Double>
        <x>369.0</x>
        <y>263.0</y>
        <width>8.0</width>
        <height>8.0</height>
      </java.awt.geom.Rectangle2D_-Double>
      <java.awt.geom.Rectangle2D_-Double>
        <x>323.0</x>
        <y>204.0</y>
        <width>8.0</width>
        <height>8.0</height>
      </java.awt.geom.Rectangle2D_-Double>
    </boundries>
    <x1>373</x1>
    <y1>267</y1>
    <x2>327</x2>
    <y2>208</y2>
    <xBounds>
      <int>373</int>
      <int>327</int>
    </xBounds>
    <yBounds>
      <int>267</int>
      <int>208</int>
    </yBounds>
  </Line>
  <Line>
    <color reference="../../Circle/color"/>
    <thickness>3</thickness>
    <isDashed>false</isDashed>
    <isFilled>false</isFilled>
    <boundries>
      <java.awt.geom.Rectangle2D_-Double>
        <x>290.0</x>
        <y>414.0</y>
        <width>8.0</width>
        <height>8.0</height>
      </java.awt.geom.Rectangle2D_-Double>
      <java.awt.geom.Rectangle2D_-Double>
        <x>367.0</x>
        <y>266.0</y>
        <width>8.0</width>
        <height>8.0</height>
      </java.awt.geom.Rectangle2D_-Double>
    </boundries>
    <x1>294</x1>
    <y1>418</y1>
    <x2>371</x2>
    <y2>270</y2>
    <xBounds>
      <int>294</int>
      <int>371</int>
    </xBounds>
    <yBounds>
      <int>418</int>
      <int>270</int>
    </yBounds>
  </Line>
  <Line>
    <color reference="../../Line[3]/color"/>
    <thickness>3</thickness>
    <isDashed>false</isDashed>
    <isFilled>false</isFilled>
    <boundries>
      <java.awt.geom.Rectangle2D_-Double>
        <x>394.0</x>
        <y>234.0</y>
        <width>8.0</width>
        <height>8.0</height>
      </java.awt.geom.Rectangle2D_-Double>
      <java.awt.geom.Rectangle2D_-Double>
        <x>291.0</x>
        <y>416.0</y>
        <width>8.0</width>
        <height>8.0</height>
      </java.awt.geom.Rectangle2D_-Double>
    </boundries>
    <x1>398</x1>
    <y1>238</y1>
    <x2>295</x2>
    <y2>420</y2>
    <xBounds>
      <int>398</int>
      <int>295</int>
    </xBounds>
    <yBounds>
      <int>238</int>
      <int>420</int>
    </yBounds>
  </Line>
  <Circle>
    <color>
      <red>0</red>
      <green>0</green>
      <blue>0</blue>
      <alpha>255</alpha>
    </color>
    <fill>
      <red>255</red>
      <green>255</green>
      <blue>0</blue>
      <alpha>255</alpha>
    </fill>
    <thickness>3</thickness>
    <isDashed>false</isDashed>
    <isFilled>true</isFilled>
    <boundries>
      <java.awt.geom.Rectangle2D_-Double>
        <x>252.0</x>
        <y>155.0</y>
        <width>8.0</width>
        <height>8.0</height>
      </java.awt.geom.Rectangle2D_-Double>
      <java.awt.geom.Rectangle2D_-Double>
        <x>245.0</x>
        <y>162.0</y>
        <width>8.0</width>
        <height>8.0</height>
      </java.awt.geom.Rectangle2D_-Double>
      <java.awt.geom.Rectangle2D_-Double>
        <x>259.0</x>
        <y>162.0</y>
        <width>8.0</width>
        <height>8.0</height>
      </java.awt.geom.Rectangle2D_-Double>
      <java.awt.geom.Rectangle2D_-Double>
        <x>252.0</x>
        <y>169.0</y>
        <width>8.0</width>
        <height>8.0</height>
      </java.awt.geom.Rectangle2D_-Double>
    </boundries>
    <a>14</a>
    <b>14</b>
    <x>249</x>
    <y>159</y>
    <xBounds>
      <int>256</int>
      <int>249</int>
      <int>263</int>
      <int>256</int>
    </xBounds>
    <yBounds>
      <int>159</int>
      <int>166</int>
      <int>166</int>
      <int>173</int>
    </yBounds>
    <E class="java.awt.geom.Ellipse2D$Double">
      <x>249.0</x>
      <y>159.0</y>
      <width>14.0</width>
      <height>14.0</height>
    </E>
    <isCircle>true</isCircle>
  </Circle>
  <Circle>
    <color reference="../../Circle[5]/color"/>
    <fill reference="../../Circle[5]/fill"/>
    <thickness>3</thickness>
    <isDashed>false</isDashed>
    <isFilled>true</isFilled>
    <boundries>
      <java.awt.geom.Rectangle2D_-Double>
        <x>245.0</x>
        <y>183.0</y>
        <width>8.0</width>
        <height>8.0</height>
      </java.awt.geom.Rectangle2D_-Double>
      <java.awt.geom.Rectangle2D_-Double>
        <x>239.0</x>
        <y>189.0</y>
        <width>8.0</width>
        <height>8.0</height>
      </java.awt.geom.Rectangle2D_-Double>
      <java.awt.geom.Rectangle2D_-Double>
        <x>252.0</x>
        <y>189.0</y>
        <width>8.0</width>
        <height>8.0</height>
      </java.awt.geom.Rectangle2D_-Double>
      <java.awt.geom.Rectangle2D_-Double>
        <x>245.0</x>
        <y>196.0</y>
        <width>8.0</width>
        <height>8.0</height>
      </java.awt.geom.Rectangle2D_-Double>
    </boundries>
    <a>13</a>
    <b>13</b>
    <x>243</x>
    <y>187</y>
    <xBounds>
      <int>249</int>
      <int>243</int>
      <int>256</int>
      <int>249</int>
    </xBounds>
    <yBounds>
      <int>187</int>
      <int>193</int>
      <int>193</int>
      <int>200</int>
    </yBounds>
    <E class="java.awt.geom.Ellipse2D$Double">
      <x>243.0</x>
      <y>187.0</y>
      <width>13.0</width>
      <height>13.0</height>
    </E>
    <isCircle>true</isCircle>
  </Circle>
  <Circle>
    <color reference="../../Circle[5]/color"/>
    <fill reference="../../Circle[5]/fill"/>
    <thickness>3</thickness>
    <isDashed>false</isDashed>
    <isFilled>true</isFilled>
    <boundries>
      <java.awt.geom.Rectangle2D_-Double>
        <x>284.0</x>
        <y>152.0</y>
        <width>8.0</width>
        <height>8.0</height>
      </java.awt.geom.Rectangle2D_-Double>
      <java.awt.geom.Rectangle2D_-Double>
        <x>276.0</x>
        <y>160.0</y>
        <width>8.0</width>
        <height>8.0</height>
      </java.awt.geom.Rectangle2D_-Double>
      <java.awt.geom.Rectangle2D_-Double>
        <x>292.0</x>
        <y>160.0</y>
        <width>8.0</width>
        <height>8.0</height>
      </java.awt.geom.Rectangle2D_-Double>
      <java.awt.geom.Rectangle2D_-Double>
        <x>284.0</x>
        <y>168.0</y>
        <width>8.0</width>
        <height>8.0</height>
      </java.awt.geom.Rectangle2D_-Double>
    </boundries>
    <a>16</a>
    <b>16</b>
    <x>280</x>
    <y>156</y>
    <xBounds>
      <int>288</int>
      <int>280</int>
      <int>296</int>
      <int>288</int>
    </xBounds>
    <yBounds>
      <int>156</int>
      <int>164</int>
      <int>164</int>
      <int>172</int>
    </yBounds>
    <E class="java.awt.geom.Ellipse2D$Double">
      <x>280.0</x>
      <y>156.0</y>
      <width>16.0</width>
      <height>16.0</height>
    </E>
    <isCircle>true</isCircle>
  </Circle>
  <Circle>
    <color reference="../../Circle/color"/>
    <fill reference="../../Circle/fill"/>
    <thickness>3</thickness>
    <isDashed>false</isDashed>
    <isFilled>true</isFilled>
    <boundries>
      <java.awt.geom.Rectangle2D_-Double>
        <x>298.0</x>
        <y>198.0</y>
        <width>8.0</width>
        <height>8.0</height>
      </java.awt.geom.Rectangle2D_-Double>
      <java.awt.geom.Rectangle2D_-Double>
        <x>280.0</x>
        <y>216.0</y>
        <width>8.0</width>
        <height>8.0</height>
      </java.awt.geom.Rectangle2D_-Double>
      <java.awt.geom.Rectangle2D_-Double>
        <x>317.0</x>
        <y>216.0</y>
        <width>8.0</width>
        <height>8.0</height>
      </java.awt.geom.Rectangle2D_-Double>
      <java.awt.geom.Rectangle2D_-Double>
        <x>298.0</x>
        <y>235.0</y>
        <width>8.0</width>
        <height>8.0</height>
      </java.awt.geom.Rectangle2D_-Double>
    </boundries>
    <a>37</a>
    <b>37</b>
    <x>284</x>
    <y>202</y>
    <xBounds>
      <int>302</int>
      <int>284</int>
      <int>321</int>
      <int>302</int>
    </xBounds>
    <yBounds>
      <int>202</int>
      <int>220</int>
      <int>220</int>
      <int>239</int>
    </yBounds>
    <E class="java.awt.geom.Ellipse2D$Double">
      <x>284.0</x>
      <y>202.0</y>
      <width>37.0</width>
      <height>37.0</height>
    </E>
    <isCircle>true</isCircle>
  </Circle>
  <Circle>
    <color reference="../../Circle[5]/fill"/>
    <fill reference="../../Circle[5]/fill"/>
    <thickness>3</thickness>
    <isDashed>false</isDashed>
    <isFilled>true</isFilled>
    <boundries>
      <java.awt.geom.Rectangle2D_-Double>
        <x>293.0</x>
        <y>184.0</y>
        <width>8.0</width>
        <height>8.0</height>
      </java.awt.geom.Rectangle2D_-Double>
      <java.awt.geom.Rectangle2D_-Double>
        <x>286.0</x>
        <y>191.0</y>
        <width>8.0</width>
        <height>8.0</height>
      </java.awt.geom.Rectangle2D_-Double>
      <java.awt.geom.Rectangle2D_-Double>
        <x>300.0</x>
        <y>191.0</y>
        <width>8.0</width>
        <height>8.0</height>
      </java.awt.geom.Rectangle2D_-Double>
      <java.awt.geom.Rectangle2D_-Double>
        <x>293.0</x>
        <y>198.0</y>
        <width>8.0</width>
        <height>8.0</height>
      </java.awt.geom.Rectangle2D_-Double>
    </boundries>
    <a>14</a>
    <b>14</b>
    <x>290</x>
    <y>188</y>
    <xBounds>
      <int>297</int>
      <int>290</int>
      <int>304</int>
      <int>297</int>
    </xBounds>
    <yBounds>
      <int>188</int>
      <int>195</int>
      <int>195</int>
      <int>202</int>
    </yBounds>
    <E class="java.awt.geom.Ellipse2D$Double">
      <x>290.0</x>
      <y>188.0</y>
      <width>14.0</width>
      <height>14.0</height>
    </E>
    <isCircle>true</isCircle>
  </Circle>
  <Circle>
    <color reference="../../Circle[5]/fill"/>
    <fill reference="../../Circle[5]/fill"/>
    <thickness>3</thickness>
    <isDashed>false</isDashed>
    <isFilled>true</isFilled>
    <boundries>
      <java.awt.geom.Rectangle2D_-Double>
        <x>277.0</x>
        <y>197.0</y>
        <width>8.0</width>
        <height>8.0</height>
      </java.awt.geom.Rectangle2D_-Double>
      <java.awt.geom.Rectangle2D_-Double>
        <x>271.0</x>
        <y>203.0</y>
        <width>8.0</width>
        <height>8.0</height>
      </java.awt.geom.Rectangle2D_-Double>
      <java.awt.geom.Rectangle2D_-Double>
        <x>284.0</x>
        <y>203.0</y>
        <width>8.0</width>
        <height>8.0</height>
      </java.awt.geom.Rectangle2D_-Double>
      <java.awt.geom.Rectangle2D_-Double>
        <x>277.0</x>
        <y>210.0</y>
        <width>8.0</width>
        <height>8.0</height>
      </java.awt.geom.Rectangle2D_-Double>
    </boundries>
    <a>13</a>
    <b>13</b>
    <x>275</x>
    <y>201</y>
    <xBounds>
      <int>281</int>
      <int>275</int>
      <int>288</int>
      <int>281</int>
    </xBounds>
    <yBounds>
      <int>201</int>
      <int>207</int>
      <int>207</int>
      <int>214</int>
    </yBounds>
    <E class="java.awt.geom.Ellipse2D$Double">
      <x>275.0</x>
      <y>201.0</y>
      <width>13.0</width>
      <height>13.0</height>
    </E>
    <isCircle>true</isCircle>
  </Circle>
  <Circle>
    <color reference="../../Circle/color"/>
    <fill reference="../../Triangle/fill"/>
    <thickness>1</thickness>
    <isDashed>false</isDashed>
    <isFilled>true</isFilled>
    <boundries>
      <java.awt.geom.Rectangle2D_-Double>
        <x>268.0</x>
        <y>159.0</y>
        <width>8.0</width>
        <height>8.0</height>
      </java.awt.geom.Rectangle2D_-Double>
      <java.awt.geom.Rectangle2D_-Double>
        <x>248.0</x>
        <y>179.0</y>
        <width>8.0</width>
        <height>8.0</height>
      </java.awt.geom.Rectangle2D_-Double>
      <java.awt.geom.Rectangle2D_-Double>
        <x>288.0</x>
        <y>179.0</y>
        <width>8.0</width>
        <height>8.0</height>
      </java.awt.geom.Rectangle2D_-Double>
      <java.awt.geom.Rectangle2D_-Double>
        <x>268.0</x>
        <y>199.0</y>
        <width>8.0</width>
        <height>8.0</height>
      </java.awt.geom.Rectangle2D_-Double>
    </boundries>
    <a>40</a>
    <b>40</b>
    <x>252</x>
    <y>163</y>
    <xBounds>
      <int>272</int>
      <int>252</int>
      <int>292</int>
      <int>272</int>
    </xBounds>
    <yBounds>
      <int>163</int>
      <int>183</int>
      <int>183</int>
      <int>203</int>
    </yBounds>
    <E class="java.awt.geom.Ellipse2D$Double">
      <x>252.0</x>
      <y>163.0</y>
      <width>40.0</width>
      <height>40.0</height>
    </E>
    <isCircle>true</isCircle>
  </Circle>
</list>
